{
  "shoppingLists": [
    {
      "id": 1,
      "listName": "First list",
      "listData": [
        {
          "id": 1,
          "itemName": "Milk",
          "qty": 1,
          "checked": true
        },
        {
          "id": 2,
          "itemName": "Eggs",
          "qty": 10,
          "checked": false
        },
        {
          "id": 3,
          "itemName": "Bread",
          "qty": 2,
          "checked": true
        }
      ]
    },
    {
      "id": 2,
      "listName": "Second list",
      "listData": [
        {
          "id": 1,
          "itemName": "Milk",
          "qty": 1,
          "checked": true
        },
        {
          "id": 2,
          "itemName": "Eggs",
          "qty": 10,
          "checked": false
        },
        {
          "id": 3,
          "itemName": "Bread",
          "qty": 2,
          "checked": true
        }
      ]
    }
  ],
  "currentList": {},
  "suggestions": [
    {
      "title": "eggs",
      "id": 1
    },
    {
      "title": "eggplant",
      "id": 2
    },
    {
      "title": "milk",
      "id": 3
    },
    {
      "title": "milkshake",
      "id": 4
    },
    {
      "title": "milkbread",
      "id": 5
    }
  ]
}